README.md
setup.py
src/keras_video/__init__.py
src/keras_video/flow.py
src/keras_video/generator.py
src/keras_video/sliding.py
src/keras_video/utils.py
src/keras_video_generators.egg-info/PKG-INFO
src/keras_video_generators.egg-info/SOURCES.txt
src/keras_video_generators.egg-info/dependency_links.txt
src/keras_video_generators.egg-info/requires.txt
src/keras_video_generators.egg-info/top_level.txt