Metadata-Version: 2.1
Name: keras-video-generators
Version: 1.0.7
Summary: Keras sequence generators for video data
Home-page: https://github.com/metal3d/keras-video-generators
Author: Patrice Ferlet
Author-email: metal3d@gmail.com
License: MIT
Platform: UNKNOWN
